slidedeck/__init__.py
slidedeck/create.py
slidedeck/mdx_mathjax.py
slidedeck/render.py
slidedeck/watch.py
slidedeck/data/base.html
slidedeck/data/slides.md
slidedeck/data/figures/200px-6n-graf.svg.png
slidedeck/data/figures/gpcr_activation.png
slidedeck/data/js/modernizr.custom.45394.js
slidedeck/data/js/slide-controller.js
slidedeck/data/js/slide-deck.js
slidedeck/data/js/slides.js
slidedeck/data/theme/css/custom.css
slidedeck/data/theme/css/default.css
slidedeck/data/theme/css/phone.css
slidedeck/data/theme/scss/_base.scss
slidedeck/data/theme/scss/default.scss
slidedeck/data/theme/scss/phone.scss
slidedeck/scripts/__init__.py
slidedeck/scripts/slidedeck.py
slidedeck-0.14.dist-info/DESCRIPTION.rst
slidedeck-0.14.dist-info/entry_points.txt
slidedeck-0.14.dist-info/METADATA
slidedeck-0.14.dist-info/metadata.json
slidedeck-0.14.dist-info/RECORD
slidedeck-0.14.dist-info/top_level.txt
slidedeck-0.14.dist-info/WHEEL
