Metadata-Version: 1.1
Name: slidedeck
Version: 0.14
Summary: Slidedeck: Kickass-beautiful HTML5 slides in markdown
Home-page: https://github.com/rmcgibbo/slidedeck
Author: Robert McGibbon
Author-email: rmcgibbo@gmail.com
License: UNKNOWN
Platform: Linux
Platform: Mac OS-X
Platform: Unix
Classifier: Development Status :: 3 - Alpha
Classifier: Intended Audience :: Science/Research
Classifier: License :: Public Domain
Classifier: Programming Language :: Python
Classifier: Operating System :: OS Independent
Classifier: Topic :: Internet :: WWW/HTTP
